auto8/__init__.py
auto8/main.py
auto8/fixers/__init__.py
auto8/fixers/e127_continuation_line_over_indented.py
auto8/fixers/e128_continuation_line_under_indented.py
auto8/fixers/e302_expected_two_blank_lines.py
auto8/fixers/e303_too_many_blank_lines.py
auto8/fixers/e501_line_too_long.py
auto8/fixers/e502_redundant_backslash.py
auto8/fixers/f401_unused_import.py
auto8/fixers/w291_trailing_whitespace.py
auto8/fixers/w292_no_newline_at_eof.py
auto8/fixers/w293_blank_line_whitespace.py
auto8-0.1.2.dist-info/LICENSE
auto8-0.1.2.dist-info/METADATA
auto8-0.1.2.dist-info/WHEEL
auto8-0.1.2.dist-info/entry_points.txt
auto8-0.1.2.dist-info/top_level.txt
auto8-0.1.2.dist-info/RECORD
