Metadata-Version: 2.1
Name: auto8
Version: 0.1.2
Summary: A tool to automatically fix flake8 issues
Home-page: https://github.com/naserjamal/auto8
Author: Naser Jamal
Author-email: naser.dll@hotmail.com
License: UNKNOWN
Platform: UNKNOWN
Classifier: Programming Language :: Python :: 3
Classifier: License :: OSI Approved :: MIT License
Classifier: Operating System :: OS Independent
License-File: LICENSE
Requires-Dist: flake8
